[
  {"name": "מינסטרונה של פירות קיץ", "issue": "199", "page": "36"},
  {"name": "מרק יוגורט קר עם אפונה וטרגון", "issue": "199", "page": "35"},
  {"name": "רוטב לסלט קיסר", "issue": "199", "page": "122"},
  {"name": "רוטב שומשום", "issue": "199", "page": "122"},
  {"name": "שייק בננות ותמרים", "issue": "199", "page": "76"},
  {"name": "אטריות סובה עם חזה עוף", "issue": "199", "page": "35"},
  {"name": "אנטריקוס ברוטב יין אדום", "issue": "199", "page": "92"},
  {"name": "כתר צלעות במרינדה של סילאן ויין", "issue": "199", "page": "68"},
  {"name": "נתחוני שייסל מוקצפים עם שעועית ירוקה חרדל וסילאן", "issue": "199", "page": "71"},
  {"name": "עדשים ביין אדום", "issue": "199", "page": "93"},
  {"name": "עוף ביין", "issue": "199", "page": "92"},
  {"name": "שוק טלה בשום ואנשובי", "issue": "199", "page": "94"},
  {"name": "בנוסח נסקון", "issue": "199", "page": "94"},
  {"name": "טורטייה דג עם סלסה בשלושה צבעים", "issue": "199", "page": "36"},
  {"name": "פול ברוטב תפוז על מצג דלעת", "issue": "199", "page": "51"},
  {"name": "פסטה בוטרנו", "issue": "199", "page": "117"},
  {"name": "קציצות דג ברוטב לימון", "issue": "199", "page": "116"},
  {"name": "כבוש וכורכום", "issue": "199", "page": "116"},
  {"name": "אפונה מאודה עם בצל חוסה", "issue": "199", "page": "95"},
  {"name": "ביייב סלק בציפוי בצק בירה", "issue": "199", "page": "54"},
  {"name": "בצלים מקורמלים בסילאן", "issue": "199", "page": "68"},
  {"name": "ברוקולי מוקרם בתנור", "issue": "199", "page": "38"},
  {"name": "כרישה בנוסח יווני", "issue": "199", "page": "95"},
  {"name": "כרישה בצירי ירקות וחמאה", "issue": "199", "page": "54"},
  {"name": "לוביה בחלב קוקוס", "issue": "199", "page": "116"},
  {"name": "מאפה ברוקולי", "issue": "199", "page": "123"},
  {"name": "מנטי במילוי דלעת ובצל", "issue": "199", "page": "121"},
  {"name": "סלט עדשים תמרים וגבינת פטה", "issue": "199", "page": "75"},
  {"name": "סלט עשבים רענן עם רימונים", "issue": "199", "page": "60"},
  {"name": "סלט של לוביה יבשה טורייה", "issue": "199", "page": "60"},
  {"name": "סלט שעועית", "issue": "199", "page": "38"},
  {"name": "סלט תאנים ואורז בר", "issue": "199", "page": "38"},
  {"name": "בוויניגרט סילאן ורוקפור", "issue": "199", "page": "71"},
  {"name": "סלט תמרים ועשבים", "issue": "199", "page": "74"},
  {"name": "סלט תרד ורימונים", "issue": "199", "page": "117"},
  {"name": "פרפלעך עם קונפי בצל", "issue": "199", "page": "58"},
  {"name": "קונפי דז", "issue": "199", "page": "58"},
  {"name": "תמרים ממולאים בגבינת עחים", "issue": "199", "page": "74"},
  {"name": "גביע שוקולד במילוי", "issue": "199", "page": "101"},
  {"name": "שוקולד מריר ומנתה", "issue": "199", "page": "101"},
  {"name": "שוקולד מריר תפוז", "issue": "199", "page": "101"},
  {"name": "גלידת יוגורט מהירה", "issue": "199", "page": "40"},
  {"name": "טארט פקאן וצנוברים עם סילאן", "issue": "199", "page": "71"},
  {"name": "כדורי תמרים ואגוזים בציפוי שומשום", "issue": "199", "page": "74"},
  {"name": "מאפינס תמרים", "issue": "199", "page": "76"},
  {"name": "מוס חלבה ואגוזים", "issue": "199", "page": "123"},
  {"name": "מוס שוקולד מהיר", "issue": "199", "page": "123"},
  {"name": "במנציסם צבעוניים", "issue": "199", "page": "102"},
  {"name": "מלית מרציפן ושוקולד חלב", "issue": "199", "page": "101"},
  {"name": "מלית קרם חלבה", "issue": "199", "page": "101"},
  {"name": "סמיפרדו סילאן ומסקרפונה", "issue": "199", "page": "71"},
  {"name": "עונת דבש", "issue": "199", "page": "55"},
  {"name": "עונת פאדי מהממת", "issue": "199", "page": "98"},
  {"name": "פינסנייר עם קרם מסקרפונה והל", "issue": "199", "page": "102"},
  {"name": "פנקוטה עם רוטב תפוחים", "issue": "199", "page": "98"},

  {"name": "גוקאמולי אבוקדו-רימונים", "issue": "206", "page": "100"},
  {"name": "חרוסת של סבתא טובה", "issue": "206", "page": "60"},
  {"name": "לימודת פירות יער", "issue": "206", "page": "103"},
  {"name": "מרח קישואים", "issue": "206", "page": "92"},
  {"name": "מרק עוף עם נודזי עגל ומנגנולד", "issue": "206", "page": "67"},
  {"name": "מרק קינאה ותרד", "issue": "206", "page": "103"},
  {"name": "שורו ואאס מרח חומוס פיקנטי", "issue": "206", "page": "83"},
  {"name": "תערובת ברברה", "issue": "206", "page": "84"},
  {"name": "קרקוט ארוחת בוקר", "issue": "206", "page": "34"},
  {"name": "קישואים ממולאים בדג ברוטב טחינה", "issue": "206", "page": "36"},
  {"name": "בסטילס קציצות תפוחי אדמה", "issue": "206", "page": "64"},
  {"name": "טריפולטייאות ממולאות בבשר", "issue": "206", "page": "64"},
  {"name": "דורו קיי ואאט קדרה חריפה של שוקי עוף ובצים", "issue": "206", "page": "83"},
  {"name": "זיל זיל טיבב ראצות בשר", "issue": "206", "page": "83"},
  {"name": "וציל בסיגון ערבוז", "issue": "206", "page": "84"},
  {"name": "טאטאקי עם ארטישוק", "issue": "206", "page": "70"},
  {"name": "ענבניות ובזיליקום", "issue": "206", "page": "115"},
  {"name": "נייד בקר קנמון ירקות שורש", "issue": "206", "page": "68"},
  {"name": "נחח שניץ צ'יצ' צלוי עם תפוחי אדמה", "issue": "206", "page": "68"},
  {"name": "תרד תורכי ואפנה", "issue": "206", "page": "68"},
  {"name": "סטייק טרטר אביבי עם פול ירוק ונענע", "issue": "206", "page": "67"},
  {"name": "ציומה", "issue": "206", "page": "60"},
  {"name": "צלי בשר עם פוד", "issue": "206", "page": "60"},
  {"name": "בלינציס ממולאים בתרד", "issue": "206", "page": "34"},
  {"name": "חורשת בסטינגיאן נזיד חצילים", "issue": "206", "page": "34"},
  {"name": "פרסי של מלכה", "issue": "206", "page": "62"},
  {"name": "טוסט פולנטה", "issue": "206", "page": "99"},
  {"name": "לחמניות פסח עם אגוזים וצימוקים", "issue": "206", "page": "103"},
  {"name": "מסר וואז תבשיל עדשים", "issue": "206", "page": "84"},
  {"name": "טוסי ירקות", "issue": "206", "page": "91"},
  {"name": "סלט ארטישוק אביבי", "issue": "206", "page": "36"},
  {"name": "סלט חצילים ויוגורט כבשים פיקנטי", "issue": "206", "page": "104"},
  {"name": "סלט סלרי ובצל ירוק", "issue": "206", "page": "104"},
  {"name": "סלט קטן של ענבניות", "issue": "206", "page": "104"},
  {"name": "פרות ירקות וכוסברה", "issue": "206", "page": "100"},
  {"name": "סלט שורשים מרוען", "issue": "206", "page": "58"},
  {"name": "סלט תפוחי אדמה סלרי", "issue": "206", "page": "58"},
  {"name": "ספוני קישואים ברוטב מרונארה", "issue": "206", "page": "92"},
  {"name": "פלאו עם פול של מלכה", "issue": "206", "page": "62"},
  {"name": "פריטטה רטוב", "issue": "206", "page": "100"},
  {"name": "פשטידת מצה וגבינות", "issue": "206", "page": "104"},
  {"name": "קישים אישיים של ירקותה ותרד", "issue": "206", "page": "99"},
  {"name": "הקנדלעך המוקצפים של פטרי", "issue": "206", "page": "33"},
  {"name": "קארי פטריות", "issue": "206", "page": "62"},
  {"name": "קוקו סבזי", "issue": "206", "page": "62"},
  {"name": "תפופי אדמה ברוטב ציילי", "issue": "206", "page": "115"},
  {"name": "אגוזים במיפל וציילי", "issue": "206", "page": "107"},
  {"name": "אנסים בוודקה וניל", "issue": "206", "page": "109"},
  {"name": "טראולכן עם פירות מיובשים", "issue": "206", "page": "63"},
  {"name": "טריפל שוקולד גבינה מסקרפונה ופוטל", "issue": "206", "page": "76"},
  {"name": "כדורי פאדני חרובים מולפטה", "issue": "206", "page": "92"},
  {"name": "מצה בריי בסוכר וקינמון", "issue": "206", "page": "40"},
  {"name": "מצות בציפוי שוקולד פיסטוקים ומשמשים מיובשים", "issue": "206", "page": "99"},
  {"name": "סהרוני בצק מלית שקדים", "issue": "206", "page": "109"},
  {"name": "סלט פירות בסבכות בסירופ דבש", "issue": "206", "page": "113"},
  {"name": "גינגיר ולמון נראס", "issue": "206", "page": "107"},
  {"name": "עוגיות גרנולה מכוסמת", "issue": "206", "page": "89"},

  {"name": "חזרת אדומה", "issue": "211", "page": "77"},
  {"name": "חזרת לבנה", "issue": "211", "page": "76"},
  {"name": "ליקר דבש", "issue": "211", "page": "88"},
  {"name": "נפילטע פיש", "issue": "211", "page": "74"},
  {"name": "כבד קציץ בסלון", "issue": "211", "page": "52"},
  {"name": "כתר צלעות טלה צלויות", "issue": "211", "page": "52"},
  {"name": "מקלובה של אורי מיקס אוכף", "issue": "211", "page": "64"},
  {"name": "סינייה של בשר, אורז וטחינה", "issue": "211", "page": "40"},
  {"name": "סלמון נורבגי בכבישה מהירה", "issue": "211", "page": "51"},
  {"name": "עוף בזיתון מרמלדת תפוחים וגינגיר", "issue": "211", "page": "80"},
  {"name": "עוף במילוי בורגול חמוציות ותפוחים", "issue": "211", "page": "80"},
  {"name": "עוף בסילאן חרדל וסידר תפוחים עם בטטות צלויות", "issue": "211", "page": "85"},
  {"name": "עוף בפסטו לימונים כבושים עם תפוחי אדמה מעוכים", "issue": "211", "page": "82"},
  {"name": "עוף ברוטב מחוץ מתוק חריף עם מנגו וכוסברה", "issue": "211", "page": "37"},
  {"name": "עופיפוניים בארמה ומיפף עם פירות מיובשים", "issue": "211", "page": "37"},
  {"name": "פוקעיה", "issue": "211", "page": "80"},
  {"name": "פטה כפרי עם פיסטוקים ותאנים", "issue": "211", "page": "85"},
  {"name": "פתאת חומוס", "issue": "211", "page": "85"},
  {"name": "קארי עוף ופטריות", "issue": "211", "page": "37"},
  {"name": "אורז אדום עם ענבניות", "issue": "211", "page": "64"},
  {"name": "זיתי קוסקוס וטרגון", "issue": "211", "page": "64"},
  {"name": "אורז אור בציר פורציינו עם חמאה מרווה ואספרגוס", "issue": "211", "page": "71"},
  {"name": "אורז בסמטי בניחוח הל עם קוביות נזר", "issue": "211", "page": "68"},
  {"name": "אפונה ירוקה וזעפרן", "issue": "211", "page": "68"},
  {"name": "אנסים לוז וקינמון", "issue": "211", "page": "57"},
  {"name": "אפוקריאקס בקרם קצפת מתובלת", "issue": "211", "page": "93"},
  {"name": "אצבעות פילו במילוי פירות מיובשים צנוברים שוקולד וחלבה בדבש לימון", "issue": "211", "page": "57"},
  {"name": "גלידת מנגו, דבש ו-5 תבלינים", "issue": "211", "page": "88"},
  {"name": "טארט קרם דבש ופוטל", "issue": "211", "page": "91"},
  {"name": "טראפלס שוקולד, דבש ותבלינים בקאקאו מתובד", "issue": "211", "page": "91"},
  {"name": "כריכי עוניות עם קרם חמאת דבש ואניס", "issue": "211", "page": "91"},
  {"name": "על סורבה ספציפורה", "issue": "211", "page": "58"},
  {"name": "עוגות דבש אישיות עם נינגיר ותאנים", "issue": "211", "page": "88"},
  {"name": "עוגת שמרים קיצית", "issue": "211", "page": "44"},
  {"name": "עוגת שקדים איטלקית", "issue": "211", "page": "42"},
  {"name": "קולאז", "issue": "211", "page": "104"},
  {"name": "קרפים בגבינת ריקוטה דבש ואוכמניות ותאנים טרות", "issue": "211", "page": "92"},

  {"name": "חזרת", "issue": "218", "page": "59"},
  {"name": "חרוסת קיבוץ גלויות", "issue": "218", "page": "58"},
  {"name": "כבד קציץ עם פיסטוקים", "issue": "218", "page": "58"},
  {"name": "מסבל אילי חזרת", "issue": "218", "page": "64"},
  {"name": "פסטו אגוזים ומנגולד", "issue": "218", "page": "59"},
  {"name": "מרק בצל ירוק", "issue": "218", "page": "62"},
  {"name": "מרק חומוס", "issue": "218", "page": "80"},
  {"name": "מרק פול ירוק מעודן", "issue": "218", "page": "62"},
  {"name": "מרק שום ירוק", "issue": "218", "page": "12"},
  {"name": "אורז מוקצץ עם עוף ופלפלים", "issue": "218", "page": "40"},
  {"name": "חזה עוף ברוטב אנשובי", "issue": "218", "page": "40"},
  {"name": "תפוחים וצלפים", "issue": "218", "page": "38"},
  {"name": "טרולי כבש בעשויות ירוקה", "issue": "218", "page": "38"},
  {"name": "כדורי דגים סנולים", "issue": "218", "page": "80"},
  {"name": "סופגניות כבש בתפוחי אדמה", "issue": "218", "page": "80"},
  {"name": "סלמון מנבטי בשר ירכבים", "issue": "218", "page": "68"},
  {"name": "עופיפוניים שינוארים 40-50 שני שום", "issue": "218", "page": "82"},
  {"name": "פילה סלמון ברוטב לסלמון לימון וצלפים", "issue": "218", "page": "68"},
  {"name": "צלי בקר במיובשים", "issue": "218", "page": "86"},
  {"name": "קציצות דגים לימונות", "issue": "218", "page": "66"},
  {"name": "קציצות קרפיון ברוטב חריימה", "issue": "218", "page": "116"},
  {"name": "רוטב ציילי חריף מחלק לסלמון", "issue": "218", "page": "68"},
  {"name": "רוטב שום רימונים ויניגר לסלמון, שוק קרם ממולאת בסרמונים", "issue": "218", "page": "68"},
  {"name": "בשר סחון וצוורים שוק טלה בקראסט של הרדל, סילאן והרים ולפסה ומלפלאות", "issue": "218", "page": "77"},
  {"name": "תבשיל טלה עם פטריות ומחין ירושלמי", "issue": "218", "page": "84"},
  {"name": "תבשיל קוביות בקר עם", "issue": "218", "page": "78"},
  {"name": "זימוק ענבניות", "issue": "218", "page": "88"},
  {"name": "אורז אדום תנור", "issue": "218", "page": "94"},
  {"name": "אורז ירוק מנביט", "issue": "218", "page": "94"},
  {"name": "אורז מצות חגיג", "issue": "218", "page": "94"},
  {"name": "אפונת שלג פרובנסאל", "issue": "218", "page": "93"},
  {"name": "וקליפות לימון", "issue": "218", "page": "93"},
  {"name": "Eton Mess", "issue": "218", "page": "111"},
  {"name": "וושרי", "issue": "218", "page": "108"},
  {"name": "טארטלט מצה במילוי קרם גבינה לימוני ומרנד", "issue": "218", "page": "55"},
  {"name": "טבעות מצה ממולאות במוס גבינה שוקולד לבן ומרנג", "issue": "218", "page": "54"},
  {"name": "טורט תפוחים ואגוזים של פס", "issue": "218", "page": "100"},

  {"name": "איולי זעפרן", "issue": "247", "page": "74"},
  {"name": "פסטו גרטניום ואוסטרחיליה", "issue": "247", "page": "16"},
  {"name": "צ'אטני ענבניות ושקדים", "issue": "247", "page": "38"},
  {"name": "קרם חצילים", "issue": "247", "page": "40"},
  {"name": "קרם ענבניות וסחון", "issue": "247", "page": "38"},
  {"name": "דג ברוטב יווני עם ענבניות זיתים ורוזמרין", "issue": "247", "page": "74"},
  {"name": "נתחי דג מרוקאי ברוטב חצילים ופלפלים", "issue": "247", "page": "78"},
  {"name": "חרוקס", "issue": "247", "page": "78"},
  {"name": "סלמון דג ישראקי", "issue": "247", "page": "38"},
  {"name": "ברוטב חמוץ מתוק סלט פלפלים קלויים עם אנשובי זיתים", "issue": "247", "page": "38"},
  {"name": "סלט תפוחי אדמה אבוקדו ונבטים", "issue": "247", "page": "40"},
  {"name": "קארי דג עם מנגו ומנגולד", "issue": "247", "page": "40"},
  {"name": "מעדה בני ישראל בבומביי", "issue": "247", "page": "76"},
  {"name": "קלדרה מרק דגים אלג'יראי עם אורז זעפרן וקליפת תפוז", "issue": "247", "page": "72"},
  {"name": "קציצות דג תורכות", "issue": "247", "page": "76"},
  {"name": "תבשיל קציצות דג חומוס וכוסברה בלימונים כבושים", "issue": "247", "page": "74"},
  {"name": "אורז בוכרי ירוק (בחש)", "issue": "247", "page": "50"},
  {"name": "בקר ממולא באורח מנגולד וחומוס", "issue": "247", "page": "50"},
  {"name": "בצלפים וכוסברה", "issue": "247", "page": "94"},
  {"name": "מושט נגינה ממולאת בדלעת ושומן כבש", "issue": "247", "page": "62"},
  {"name": "דושפרה כבש עם דובדבנים מיובשים זרעי כמון ובצלצלים", "issue": "247", "page": "66"},
  {"name": "דלעת ממולאת בתבשיל בקר", "issue": "247", "page": "92"},
  {"name": "הבאחש של פרסיליה", "issue": "247", "page": "50"},
  {"name": "כרוב ממולא בתערובת של בקר ובכבדים זיתי ואנשובי", "issue": "247", "page": "88"},
  {"name": "מלפופוניות ממולאות מיובשות", "issue": "247", "page": "88"},
  {"name": "מנממשים מיובשים עוף ממולא בחיטה בשר טחון", "issue": "247", "page": "69"},
  {"name": "עוף ממולא באורי ירושלמי", "issue": "247", "page": "90"},
  {"name": "עוף צלוי עם תאנים מייפף ומרווה", "issue": "247", "page": "46"},
  {"name": "צוואר כבש ממולא בצל מטון", "issue": "247", "page": "96"},
  {"name": "שוק טלה ואלף דברים טובים", "issue": "247", "page": "90"},
  {"name": "שוק קטון ממולא באורה מורחב ירוק", "issue": "247", "page": "92"},
  {"name": "שוק תקון ממולאת בשר, ירקות שורש ומרווה", "issue": "247", "page": "46"},
  {"name": "אורז עם ירקות כתומים", "issue": "247", "page": "52"},
  {"name": "אורז עם טריות וערמונים", "issue": "247", "page": "52"},
  {"name": "במיה אפיה עם שבבי קוקוס וציילי", "issue": "247", "page": "45"},
  {"name": "נרגרי חומוס וכוסברה וגינגיר", "issue": "247", "page": "42"},
  {"name": "חטיף גרעיני חמניות וקרמל", "issue": "247", "page": "16"},
  {"name": "חצילים עם שום וסוכר", "issue": "247", "page": "64"},
  {"name": "מאפה תאנים עם גבינת סנט מור", "issue": "247", "page": "48"},
  {"name": "סלט חריף של ענבניות בצל ירוק", "issue": "247", "page": "48"},
  {"name": "וכוסברה", "issue": "247", "page": "48"},
  {"name": "סלט סלק וזדא", "issue": "247", "page": "62"},
  {"name": "סלט עשבים עם בצל סגול תאנים וגבינה", "issue": "247", "page": "62"},
  {"name": "סלט תרד עם גבינות ענבניות ופירות קיץ", "issue": "247", "page": "36"},
  {"name": "בבקה תפוחים ואגוזים בקינמון", "issue": "247", "page": "104"},
  {"name": "דובשניות", "issue": "247", "page": "102"},
  {"name": "חלה מתוקה עם צימוקים", "issue": "247", "page": "114"},
  {"name": "טארט מסקרפונה קפה ושוקולד חלב", "issue": "247", "page": "111"},
  {"name": "מאפינס תפוחים ופיסטוק", "issue": "247", "page": "115"},
  {"name": "מרקחת של תאנים שלמות", "issue": "247", "page": "69"},
  {"name": "סהרוני פרד", "issue": "247", "page": "111"},
  {"name": "עוגיות דבש בוטנים ופיסטוק", "issue": "247", "page": "106"},
  {"name": "ואנצ'י דבש, תפוחים ובירה שחורה", "issue": "247", "page": "54"},
  {"name": "עוגת תפוחים ואגוזים", "issue": "247", "page": "102"},
  {"name": "פינציר בוטנים ודבש", "issue": "247", "page": "112"},
  {"name": "קראנץ' קרם ונל וסוכרים ופיסטוק", "issue": "247", "page": "102"},
  {"name": "ריבוני פלורנטין דבש-תפוז", "issue": "247", "page": "106"},

  {"name": "מטבוחה", "issue": "250", "page": "46"},
  {"name": "מטבוחה (אלג'יראית) של אבי לוי", "issue": "250", "page": "100"},
  {"name": "פלפלציומה", "issue": "250", "page": "47"},
  {"name": "תערובת התיבול הברברית", "issue": "250", "page": "55"},
  {"name": "מרק חרירה", "issue": "250", "page": "55"},
  {"name": "מרק עדשים תימני", "issue": "250", "page": "53"},
  {"name": "מרק לקוסקוס", "issue": "250", "page": "92"},
  {"name": "מרק עוף", "issue": "250", "page": "54"},
  {"name": "מרק שעועית תימני", "issue": "250", "page": "53"},
  {"name": "מרק רנגל תימני", "issue": "250", "page": "53"},
  {"name": "ציר בקר כהה", "issue": "250", "page": "120"},
  {"name": "ציר עוף", "issue": "250", "page": "120"},
  {"name": "קונסומה בקר או עוף", "issue": "250", "page": "118"},
  {"name": "נפילטע פיש", "issue": "250", "page": "50"},
  {"name": "דג חריף קר", "issue": "250", "page": "112"},
  {"name": "דג מרוקאי", "issue": "250", "page": "57"},
  {"name": "חריימה", "issue": "250", "page": "57"},
  {"name": "אורז בוכרי ירוק (בחש)", "issue": "250", "page": "74"},
  {"name": "אושפלאו (פלוב)", "issue": "250", "page": "72"},
  {"name": "אינגרייה", "issue": "250", "page": "72"},
  {"name": "אלבונדיגס עם חצילים", "issue": "250", "page": "82"},
  {"name": "בסטור", "issue": "250", "page": "80"},
  {"name": "גנואס קיבוץ גלויות", "issue": "250", "page": "70"},
  {"name": "גונדי", "issue": "250", "page": "82"},
  {"name": "גושט נגידה", "issue": "250", "page": "60"},
  {"name": "חורשת סבזי", "issue": "250", "page": "70"},
  {"name": "חמין קיבוץ גלויות", "issue": "250", "page": "86"},
  {"name": "כבד קציץ", "issue": "250", "page": "48"},
  {"name": "כפסטיקס דה פראסה קציצות כרישה ובשר", "issue": "250", "page": "48"},
  {"name": "כרוב ממולא בנוסח הונגרי", "issue": "250", "page": "71"},
  {"name": "לחמעגיון", "issue": "250", "page": "60"},
  {"name": "מפרום", "issue": "250", "page": "92"},
  {"name": "ספורטיסו", "issue": "250", "page": "89"},
  {"name": "עוף ממולא בבשר", "issue": "250", "page": "110"},
  {"name": "ביציים מקושקשות", "issue": "250", "page": "110"},
  {"name": "פלאו עם בניגיל", "issue": "250", "page": "68"},
  {"name": "צלי בשר של אבי", "issue": "250", "page": "108"},
  {"name": "קדרה ממולאים ברוטב רימונים", "issue": "250", "page": "68"},
  {"name": "קובה חמוסטה", "issue": "250", "page": "78"},
  {"name": "קובה מטוגנת", "issue": "250", "page": "79"},
  {"name": "קובה סלק", "issue": "250", "page": "78"},
  {"name": "קונל טלה וצנוברים של ארז קומרובסקי", "issue": "250", "page": "88"},
  {"name": "קונל שפונדרה עם פיסטוק", "issue": "250", "page": "88"},
  {"name": "קציצות בשר ואורז אלג'יריאיות", "issue": "250", "page": "107"},
  {"name": "קרפלעך", "issue": "250", "page": "81"},
  {"name": "תבית", "issue": "250", "page": "86"},
  {"name": "תבשיל זיתים ממולאים עם תפוחי אדמה ברוטב ענבניות", "issue": "250", "page": "107"},
  {"name": "אורז ירוק חמוץ עם עלי סלק", "issue": "250", "page": "108"},
  {"name": "אורז פרסי", "issue": "250", "page": "74"},
  {"name": "בואיקו", "issue": "250", "page": "63"},
  {"name": "בורקיטוס במילוי חצילים וגבינה בולגרית", "issue": "250", "page": "63"},
  {"name": "גיחון", "issue": "250", "page": "64"},
  {"name": "חבית ירק (קוקו סבזי)", "issue": "250", "page": "49"},
  {"name": "חצילים מטוגנים ברוטב שרמולה", "issue": "250", "page": "112"},
  {"name": "כרובית צהובה מטוגנת", "issue": "250", "page": "108"},
  {"name": "לביבות תפוחי אדמה (לטקעס)", "issue": "250", "page": "48"},
  {"name": "מעקודה", "issue": "250", "page": "110"},
  {"name": "סלט נזר מרוקאי", "issue": "250", "page": "50"},
  {"name": "סלט חצילים ופלפלים קלויים", "issue": "250", "page": "48"},
  {"name": "סלט עלי סלק", "issue": "250", "page": "107"},
  {"name": "סמבוסק ממולא בחומוס", "issue": "250", "page": "63"},
  {"name": "קונג'ל ירושלמי", "issue": "250", "page": "88"},
  {"name": "רויאל פטריות מיובשות", "issue": "250", "page": "120"},
  {"name": "שקשוקה", "issue": "250", "page": "47"},
  {"name": "בבקה", "issue": "250", "page": "101"},
  {"name": "גומבון", "issue": "250", "page": "97"},
  {"name": "יינו עם מלית שקדים", "issue": "250", "page": "112"},
  {"name": "מנדלברוט", "issue": "250", "page": "98"},
  {"name": "מעמולים במלית תמרים ופיסטוקים", "issue": "250", "page": "95"},
  {"name": "מקרודה", "issue": "250", "page": "96"},
  {"name": "מרוצינוס", "issue": "250", "page": "99"},
  {"name": "רולגלעך", "issue": "250", "page": "100"},
  {"name": "שטרודל", "issue": "250", "page": "96"},

  {"name": "מרק בצל ירוק", "issue": "254", "page": "76"},
  {"name": "מרק ענבניות עם ניוקי תרד של פאפי", "issue": "254", "page": "56"},
  {"name": "מרק שום ירוק", "issue": "254", "page": "76"},
  {"name": "דג בגריל עם צ'ימיציורי כוסברה", "issue": "254", "page": "88"},
  {"name": "קציצות דג בתבשיל חומוס ארטישוק ומנגולד", "issue": "254", "page": "60"},
  {"name": "קציצות פראסה ודגים עם סלסה ענבניות", "issue": "254", "page": "78"},
  {"name": "שיפודי שרימפס בחמאת זעתר", "issue": "254", "page": "88"},
  {"name": "אוכף טלה ממולא בשקדי ענל אנגוזים ושום", "issue": "254", "page": "62"},
  {"name": "גלילות מצה ממולאות בבשר ומסוגנות", "issue": "254", "page": "51"},
  {"name": "יחרבי פרנייה ונרגרי כוסברה מעושנות", "issue": "254", "page": "86"},
  {"name": "טארסקו קבצייה", "issue": "254", "page": "46"},
  {"name": "מינה-פשטידת פס", "issue": "254", "page": "50"},
  {"name": "ספריבוס חזיר כדי עוף ואגוזים", "issue": "254", "page": "86"},
  {"name": "פטה כבדי עוף ואגוזים עם פרדלה בקציצות ביס", "issue": "254", "page": "36"},
  {"name": "ברוטב שעועית ירוקה ופולי ירוק", "issue": "254", "page": "72"},
  {"name": "צ'אפלי קבב אפגני", "issue": "254", "page": "48"},
  {"name": "קבב טלה סלרי וכמהין", "issue": "254", "page": "84"},
  {"name": "קבב עוף", "issue": "254", "page": "46"},
  {"name": "קבב פאן-בלקני", "issue": "254", "page": "48"},
  {"name": "אטריות אורז ברוטב אגוזים עם באק צ'וי", "issue": "254", "page": "38"},
  {"name": "אנטיפסטו סלקים צלויים ואיקרה", "issue": "254", "page": "60"},
  {"name": "בואיקוס קשקבל ותרד", "issue": "254", "page": "78"},
  {"name": "בורקס גבינה מטוגנת", "issue": "254", "page": "50"},
  {"name": "טחינה עם המון גבינות", "issue": "254", "page": "65"},
  {"name": "כרוב גדול ניצנים צרוב", "issue": "254", "page": "42"},
  {"name": "לזניה ריקואה ותרד", "issue": "254", "page": "71"},
  {"name": "מיקס אגוזים", "issue": "254", "page": "50"},
  {"name": "סלט אנדיב רשאד ואגוזים", "issue": "254", "page": "58"},
  {"name": "סלט ברוקולי חומוס ורוזמרין ירוקה", "issue": "254", "page": "58"},
  {"name": "סלט כולאלאם ועם מאפאיה ירוקה", "issue": "254", "page": "40"},
  {"name": "סלט מחממים מרוקאי מחממים", "issue": "254", "page": "44"},
  {"name": "סלט ענבניות ובצלים קלויים", "issue": "254", "page": "84"},
  {"name": "סלט ענבניות ופלפלים קלויים", "issue": "254", "page": "84"},
  {"name": "סלט תירס גילי ובוויניגרט ספטוס", "issue": "254", "page": "83"},
  {"name": "סלט תפיא ראטה עם חומץ יין אדום שאלוט ותירס", "issue": "254", "page": "84"},
  {"name": "סלה צ'חובה עם פלפלים ותירס", "issue": "254", "page": "83"},
  {"name": "קנלוני ריקואה ותרד", "issue": "254", "page": "50"},
  {"name": "קציצות תרד גבינה ואגוזים", "issue": "254", "page": "38"},
  {"name": "קציצות תרד נגינה ואגוזים", "issue": "254", "page": "38"},
  {"name": "קרטוני אורנג'", "issue": "254", "page": "50"},
  {"name": "ריצוני ירוק עם אפונה", "issue": "254", "page": "78"},
  {"name": "תבשיל תפוחי אדמה עם ירוק ירוק", "issue": "254", "page": "78"},
  {"name": "בורמונליקוס", "issue": "254", "page": "50"},
  {"name": "החלבה הביתית של אלי אלקלעי", "issue": "254", "page": "96"},
  {"name": "החלבה הביתית של רות אוליבר", "issue": "254", "page": "97"},
  {"name": "הכנת תמצית שורש החלבה", "issue": "254", "page": "95"},
  {"name": "חיתוכיות מצה במלית שומשום", "issue": "254", "page": "51"},
  {"name": "כדורי שוקולד", "issue": "254", "page": "51"},
  {"name": "בחמניות ממולאות", "issue": "254", "page": "52"},
  {"name": "מאפינס חלבה-קינמון עם קרם חלבה", "issue": "254", "page": "106"},
  {"name": "מוס גבינה אוורירי עם קראני בוטנים", "issue": "254", "page": "52"},
  {"name": "מוס שוקולד פרווה", "issue": "254", "page": "66"},
  {"name": "מוס שוקולד פרווה", "issue": "254", "page": "66"},
  {"name": "מולפטה", "issue": "254", "page": "52"},
  {"name": "מיבי מלבה", "issue": "254", "page": "108"},
  {"name": "מתמק חלבה בציפוי אורז", "issue": "254", "page": "108"},
  {"name": "עונת חלבה בחושה", "issue": "254", "page": "36"},
  {"name": "עונת שוקוחים", "issue": "254", "page": "108"},
  {"name": "עונת שכנות ואפל חלבה שוקולד פחזניות ממולאות", "issue": "254", "page": "104"},
  {"name": "בקצפת חלבה-פיסטוק", "issue": "254", "page": "110"},
  {"name": "פרפה חלבה סילאן", "issue": "254", "page": "110"},
  {"name": "קראנץ' חלבה ושוקולד ציפס", "issue": "254", "page": "51"},
  {"name": "קראמבל תפוחים וקינמון", "issue": "254", "page": "106"},
  {"name": "שטרודל חלבה", "issue": "254", "page": "104"},

  {"name": "מרק עוף אלג'יראי", "issue": "290", "page": "34"},
  {"name": "מרק עוף תאילנדי", "issue": "290", "page": "36"},
  {"name": "מרק פול וארטישוק ירושלמי", "issue": "290", "page": "36"},
  {"name": "רוטב שום", "issue": "290", "page": "112"},
  {"name": "הגונדלעך של ארז קומרובסקי", "issue": "290", "page": "38"},
  {"name": "בוויניגרט חצילים ושום", "issue": "290", "page": "116"},
  {"name": "כבד קציץ עם לימון כרישה", "issue": "290", "page": "44"},
  {"name": "כבד קציץ של פעם", "issue": "290", "page": "42"},
  {"name": "כדורי עוף תאילנדיים", "issue": "290", "page": "40"},
  {"name": "כתף טלה בבישול איטי", "issue": "290", "page": "56"},
  {"name": "כתף ממולאת בפסטו תרד ואנצ'וי מלך", "issue": "290", "page": "54"},
  {"name": "מלית חרוסת של אבן שטיינץ", "issue": "290", "page": "54"},
  {"name": "מלית ערמונים בקר וצנוברים", "issue": "290", "page": "54"},
  {"name": "סלט עוף הים שאחרי", "issue": "290", "page": "34"},
  {"name": "סלט תפוחי אדמה בצלים מנולים וחזה אווז מעושן", "issue": "290", "page": "108"},
  {"name": "עוף במרינדה של פריקות", "issue": "290", "page": "112"},
  {"name": "צלעות כבש בלימון ורזמרין", "issue": "290", "page": "114"},
  {"name": "קבב רומני", "issue": "290", "page": "118"},
  {"name": "קציצות פראסה של ברתה", "issue": "290", "page": "50"},
  {"name": "קציצות פראסה עם אניבר", "issue": "290", "page": "52"},
  {"name": "רוסט אנטריקוט עם צלפים וחרדל", "issue": "290", "page": "112"},
  {"name": "תבשיל צוואר טלה וירקות שורש", "issue": "290", "page": "56"},
  {"name": "נפילטע פיש של שמיל", "issue": "290", "page": "46"},
  {"name": "נרגרי חומוס וזיר דגים", "issue": "290", "page": "84"},
  {"name": "מושט בטחינה", "issue": "290", "page": "87"},
  {"name": "מושט בלאדי בתנור עם עראק", "issue": "290", "page": "87"},
  {"name": "מושט בלאדי על האש", "issue": "290", "page": "82"},
  {"name": "מושט בסלרי נענע ולימון", "issue": "290", "page": "87"},
  {"name": "מושט בתנור עם עשבים וירקות", "issue": "290", "page": "88"},
  {"name": "מושט מטוגן", "issue": "290", "page": "82"},
  {"name": "מושט של שבת עם פריקה", "issue": "290", "page": "82"},
  {"name": "קציצות סלמון בקארי אפונה ירוק", "issue": "290", "page": "48"},
  {"name": "קציצות קרפיון ברוטב חריימה", "issue": "290", "page": "48"},
  {"name": "אטריות ביצים", "issue": "290", "page": "40"},
  {"name": "גראטן תפוח אדמה אישי", "issue": "290", "page": "58"},
  {"name": "גראטן תפוחי אדמה בקארי", "issue": "290", "page": "60"},
  {"name": "כרוב בוויניגרט קימל", "issue": "290", "page": "116"},
  {"name": "כרוביות וכרוב כבוש", "issue": "290", "page": "111"},
  {"name": "לחמניות של פס", "issue": "290", "page": "30"},
  {"name": "לפתות וסלקים מותמצים", "issue": "290", "page": "111"},
  {"name": "מאפינה גבינה", "issue": "290", "page": "32"},
  {"name": "מאפינס פיצה", "issue": "290", "page": "32"},
  {"name": "מנדרה אורז וחומוס עם כרוביות צלויה", "issue": "290", "page": "62"},
  {"name": "ממלינה עם חלמונים", "issue": "290", "page": "114"},
  {"name": "סלט חצילים רומני בגריל פחמים", "issue": "290", "page": "108"},
  {"name": "ענבניות שרי כבושות", "issue": "290", "page": "111"},
  {"name": "עונת תפוחי אדמה", "issue": "290", "page": "58"},
  {"name": "פופאוברס", "issue": "290", "page": "32"},
  {"name": "פטה טופו וקישוי", "issue": "290", "page": "44"},
  {"name": "קונגל תפוחי אדמה", "issue": "290", "page": "58"},
  {"name": "קציצות כרישה תפוחי אדמה וכרוביות", "issue": "290", "page": "52"},
  {"name": "קרם לבנה וברוקולי", "issue": "290", "page": "88"},
  {"name": "קרם שעועית לבנה", "issue": "290", "page": "108"},
  {"name": "שום קונפי", "issue": "290", "page": "118"},
  {"name": "תפוחי אדמה אפויים בתבלינים צהובים וקוקוס", "issue": "290", "page": "58"},
  {"name": "תפוחי אדמה זעירים מוקצפים בחמאת שום שמיר", "issue": "290", "page": "60"},
  {"name": "תפוחי אדמה מושחמים", "issue": "290", "page": "60"},
  {"name": "תפוחי אדמה מעוכים עם רוזמרין ולימון", "issue": "290", "page": "60"},
  {"name": "איים צפים באנגלז לבנדר", "issue": "290", "page": "102"},
  {"name": "אלסקה אפויה", "issue": "290", "page": "98"},
  {"name": "טריפל זוז וקינמון", "issue": "290", "page": "100"},
  {"name": "נמסיס עם קרם שיבוסט נענע", "issue": "290", "page": "100"},
  {"name": "פבלובה לימון ופירות יער", "issue": "290", "page": "96"},
  {"name": "קונקורד טירמיסו", "issue": "290", "page": "94"},
  {"name": "קרם גבינה ומרנג לימון", "issue": "290", "page": "102"}
]
